SUM_4291/__init__.py
SUM_4291-0.0.1.dist-info/LICENSE.txt
SUM_4291-0.0.1.dist-info/METADATA
SUM_4291-0.0.1.dist-info/WHEEL
SUM_4291-0.0.1.dist-info/top_level.txt
SUM_4291-0.0.1.dist-info/RECORD
