Metadata-Version: 2.1
Name: SUM-4291
Version: 0.0.1
Summary: adding number
Home-page: UNKNOWN
Author: Murtaza Abbas
Author-email: szaidi399@gmail.com
License: UNKNOWN
Platform: UNKNOWN
Classifier: Programming Language :: Python :: 3
Classifier: License :: OSI Approved :: MIT License
Classifier: Operating System :: OS Independent
